image_match/__init__.py
image_match/elasticsearch_driver.py
image_match/goldberg.py
image_match/mongodb_driver.py
image_match/signature_database_base.py
tests/__init__.py
tests/test_elasticsearch_driver.py
tests/test_elasticsearch_driver_metadata_as_nested.py
tests/test_goldberg.py
image_match3-1.1.3.dist-info/LICENSES.md
image_match3-1.1.3.dist-info/METADATA
image_match3-1.1.3.dist-info/WHEEL
image_match3-1.1.3.dist-info/top_level.txt
image_match3-1.1.3.dist-info/zip-safe
image_match3-1.1.3.dist-info/RECORD
